[
  {
    "Bleed": "0",
    "CD": "4000",
    "Condition": "1",
    "Curse": "0",
    "ES": 0,
    "Freeze": "0",
    "Group": "Life",
    "GroupCD": "150",
    "Ignite": "0",
    "Key": "1",
    "Life": 95,
    "MainAttack": "0",
    "MainAttackRelease": "0",
    "Mana": 0,
    "Move": "0",
    "Poison": "0",
    "PopAll": "1",
    "ResetCooldownAtEnergyShieldPercentage": "0",
    "ResetCooldownAtEnergyShieldPercentageInput": "0",
    "ResetCooldownAtHealthPercentage": "0",
    "ResetCooldownAtHealthPercentageInput": "0",
    "ResetCooldownAtManaPercentage": "0",
    "ResetCooldownAtManaPercentageInput": "0",
    "SecondaryAttack": "0",
    "SecondaryAttackRelease": "0",
    "Shock": "0",
    "Slot": 1,
    "Type": "Flask"
  },
  {
    "Bleed": "0",
    "CD": "5000",
    "Condition": "1",
    "Curse": "0",
    "ES": 0,
    "Freeze": "0",
    "Group": "Mana",
    "GroupCD": "150",
    "Ignite": "0",
    "Key": "2",
    "Life": 0,
    "MainAttack": "0",
    "MainAttackRelease": "0",
    "Mana": 8,
    "Move": "0",
    "Poison": "0",
    "PopAll": "1",
    "ResetCooldownAtEnergyShieldPercentage": "0",
    "ResetCooldownAtEnergyShieldPercentageInput": "0",
    "ResetCooldownAtHealthPercentage": "0",
    "ResetCooldownAtHealthPercentageInput": "0",
    "ResetCooldownAtManaPercentage": "0",
    "ResetCooldownAtManaPercentageInput": "0",
    "SecondaryAttack": "0",
    "SecondaryAttackRelease": "0",
    "Shock": "0",
    "Slot": 2,
    "Type": "Flask"
  },
  {
    "Bleed": "0",
    "CD": "5000",
    "Condition": "1",
    "Curse": "0",
    "ES": 0,
    "Freeze": "0",
    "Group": "f3",
    "GroupCD": "150",
    "Ignite": "0",
    "Key": "3",
    "Life": 0,
    "MainAttack": "1",
    "MainAttackRelease": "0",
    "Mana": 0,
    "Move": "0",
    "Poison": "0",
    "PopAll": "1",
    "ResetCooldownAtEnergyShieldPercentage": "0",
    "ResetCooldownAtEnergyShieldPercentageInput": "0",
    "ResetCooldownAtHealthPercentage": "0",
    "ResetCooldownAtHealthPercentageInput": "0",
    "ResetCooldownAtManaPercentage": "0",
    "ResetCooldownAtManaPercentageInput": "0",
    "SecondaryAttack": "1",
    "SecondaryAttackRelease": "0",
    "Shock": "0",
    "Slot": 3,
    "Type": "Flask"
  },
  {
    "Bleed": "0",
    "CD": "5000",
    "Condition": "1",
    "Curse": "0",
    "ES": 0,
    "Freeze": "0",
    "Group": "f4",
    "GroupCD": "150",
    "Ignite": "0",
    "Key": "4",
    "Life": 0,
    "MainAttack": "1",
    "MainAttackRelease": "0",
    "Mana": 0,
    "Move": "0",
    "Poison": "0",
    "PopAll": "1",
    "ResetCooldownAtEnergyShieldPercentage": "0",
    "ResetCooldownAtEnergyShieldPercentageInput": "0",
    "ResetCooldownAtHealthPercentage": "0",
    "ResetCooldownAtHealthPercentageInput": "0",
    "ResetCooldownAtManaPercentage": "0",
    "ResetCooldownAtManaPercentageInput": "0",
    "SecondaryAttack": "1",
    "SecondaryAttackRelease": "0",
    "Shock": "0",
    "Slot": 4,
    "Type": "Flask"
  },
  {
    "Bleed": "0",
    "CD": "5000",
    "Condition": "1",
    "Curse": "0",
    "ES": 0,
    "Freeze": "0",
    "Group": "QuickSilver",
    "GroupCD": "150",
    "Ignite": "0",
    "Key": "5",
    "Life": 0,
    "MainAttack": "1",
    "MainAttackRelease": "0",
    "Mana": 0,
    "Move": "1",
    "Poison": "0",
    "PopAll": "1",
    "ResetCooldownAtEnergyShieldPercentage": "0",
    "ResetCooldownAtEnergyShieldPercentageInput": "0",
    "ResetCooldownAtHealthPercentage": "0",
    "ResetCooldownAtHealthPercentageInput": "0",
    "ResetCooldownAtManaPercentage": "0",
    "ResetCooldownAtManaPercentageInput": "0",
    "SecondaryAttack": "1",
    "SecondaryAttackRelease": "0",
    "Shock": "0",
    "Slot": 5,
    "Type": "Flask"
  }
]